imsi/__init__.py
imsi/_version.py
imsi/imsi.site.rc
imsi/cli/__init__.py
imsi/cli/cli_snapshot_state.sh
imsi/cli/core_cli.py
imsi/cli/core_tracking.py
imsi/cli/entry.py
imsi/cli/lazy.py
imsi/cli/post_install.py
imsi/cli/sectioned_group.py
imsi/config_manager/.gitignore
imsi/config_manager/__init__.py
imsi/config_manager/config_manager.py
imsi/config_manager/databases.py
imsi/config_manager/tests.py
imsi/config_manager/schema/__init__.py
imsi/config_manager/schema/compiler.py
imsi/config_manager/schema/components.py
imsi/config_manager/schema/experiment.py
imsi/config_manager/schema/machine.py
imsi/config_manager/schema/model.py
imsi/config_manager/schema/post_processing.py
imsi/config_manager/schema/sequencing.py
imsi/config_manager/schema/setup_params.py
imsi/config_manager/schema/types.py
imsi/config_manager/schema/utilities.py
imsi/scheduler_interface/__init__.py
imsi/scheduler_interface/scheduler_tools.py
imsi/scheduler_interface/schedulers.py
imsi/sequencer_interface/__init__.py
imsi/sequencer_interface/iss_cap.py
imsi/sequencer_interface/maestro_cap.py
imsi/sequencer_interface/maestro_status.py
imsi/sequencer_interface/sequencers.py
imsi/shell_interface/__init__.py
imsi/shell_interface/config_hooks_collection.py
imsi/shell_interface/config_hooks_collection_config.yaml
imsi/shell_interface/config_hooks_manager.py
imsi/shell_interface/parse_dbs_example.py
imsi/shell_interface/shell_comp_environment.py
imsi/shell_interface/shell_config_parameters.py
imsi/shell_interface/shell_diag_parameters.py
imsi/shell_interface/shell_inputs_outputs.py
imsi/shell_interface/shell_interface_manager.py
imsi/shell_interface/shell_interface_utilities.py
imsi/shell_interface/shell_timing_vars.py
imsi/tools/__init__.py
imsi/tools/disk_tools/__init__.py
imsi/tools/disk_tools/disk_tools.py
imsi/tools/disk_tools/disk_tools_cli.py
imsi/tools/ensemble/README.md
imsi/tools/ensemble/__init__.py
imsi/tools/ensemble/all_supported_exp.yaml
imsi/tools/ensemble/config.py
cimsi-0.8.3.dist-info/METADATA
cimsi-0.8.3.dist-info/WHEEL
cimsi-0.8.3.dist-info/entry_points.txt
cimsi-0.8.3.dist-info/top_level.txt
cimsi-0.8.3.dist-info/RECORD
